flask_perm/__init__.py
flask_perm/admin.py
flask_perm/api.py
flask_perm/app.py
flask_perm/core.py
flask_perm/models.py
flask_perm/script.py
flask_perm/services/__init__.py
flask_perm/services/permission.py
flask_perm/services/super_admin.py
flask_perm/services/user_group.py
flask_perm/services/user_group_member.py
flask_perm/services/user_group_permission.py
flask_perm/services/user_permission.py
flask_perm/services/verification.py
flask_perm/static/admin.js
flask_perm/static/ng-admin.min.css
flask_perm/static/ng-admin.min.js
flask_perm/templates/perm-admin/index.html
flask_perm/templates/perm-admin/login.html
Flask_Perm-0.2.8.dist-info/DESCRIPTION.rst
Flask_Perm-0.2.8.dist-info/METADATA
Flask_Perm-0.2.8.dist-info/metadata.json
Flask_Perm-0.2.8.dist-info/RECORD
Flask_Perm-0.2.8.dist-info/top_level.txt
Flask_Perm-0.2.8.dist-info/WHEEL
