Metadata-Version: 2.0
Name: Flask-Perm
Version: 0.2.8
Summary: Flask Permission Management Extension
Home-page: https://github.com/soasme/flask-perm
Author: Ju Lin
Author-email: soasme@gmail.com
License: MIT
Platform: any
Classifier: Framework :: Flask
Classifier: Natural Language :: English
Classifier: Environment :: Web Environment
Classifier: Intended Audience :: Developers
Classifier: License :: OSI Approved :: MIT License
Classifier: Operating System :: OS Independent
Classifier: Programming Language :: Python
Classifier: Topic :: Internet :: WWW/HTTP :: Dynamic Content
Classifier: Topic :: Software Development :: Libraries :: Python Modules
Requires-Dist: Flask
Requires-Dist: Flask-SQLAlchemy
Requires-Dist: Flask-Bcrypt
